Metadata-Version: 2.1
Name: waterlog
Version: 1.0.0
Summary: A simple wrapper around the logging module with sane defaults.
Home-page: https://github.com/lainproliant/waterlog
Author: Lain Musgrove (lainproliant)
Author-email: lainproliant@gmail.com
License: BSD
Keywords: text log logging logger
Classifier: Development Status :: 5 - Production/Stable
Classifier: Intended Audience :: Developers
Classifier: Topic :: Software Development :: Libraries :: Application Frameworks
Classifier: License :: OSI Approved :: BSD License
Classifier: Programming Language :: Python :: 3.10
Classifier: Programming Language :: Python :: 3.11
